pdf4py/__init__.py
pdf4py/_charset.py
pdf4py/_decoders.py
pdf4py/_document.py
pdf4py/_lexer.py
pdf4py/document.py
pdf4py/exceptions.py
pdf4py/parser.py
pdf4py/types.py
pdf4py/_security/__init__.py
pdf4py/_security/aes.py
pdf4py/_security/rc4.py
pdf4py/_security/securityhandler.py
tests/__init__.py
tests/__main__.py
tests/aes_unit_tests.py
tests/context.py
tests/decoders_unit_tests.py
tests/decrypt_unit_tests.py
tests/functional_tests.py
tests/unit_tests.py
pdf4py-0.1.0.dist-info/LICENSE
pdf4py-0.1.0.dist-info/METADATA
pdf4py-0.1.0.dist-info/WHEEL
pdf4py-0.1.0.dist-info/top_level.txt
pdf4py-0.1.0.dist-info/RECORD
