Metadata-Version: 2.1
Name: pdf4py
Version: 0.1.0
Summary: A PDF parser written in Python3 with no external dependencies.
Home-page: https://github.com/Halolegend94/pdf4py
Author: Cristian Di Pietrantonio
Author-email: cristiandipietrantonio@gmail.com
License: UNKNOWN
Platform: UNKNOWN
Classifier: Programming Language :: Python :: 3
Classifier: License :: OSI Approved :: MIT License
Classifier: Operating System :: OS Independent
Requires-Python: >=3.4
